package/__init__.py
package/code_file.py
101703383_python_package2-0.0.3.dist-info/METADATA
101703383_python_package2-0.0.3.dist-info/WHEEL
101703383_python_package2-0.0.3.dist-info/top_level.txt
101703383_python_package2-0.0.3.dist-info/RECORD
