Metadata-Version: 2.1
Name: 101703383-python-package2
Version: 0.0.3
Summary: This is my second package in python.
Home-page: https://github.com/pypa/sampleproject
Author: Parteek Satija
Author-email: psatija_be17@thapar.edu
License: UNKNOWN
Platform: UNKNOWN
Classifier: Programming Language :: Python :: 3
Classifier: License :: OSI Approved :: MIT License
Classifier: Operating System :: OS Independent
Requires-Python: >=3.6
